u2net_fast/__init__.py
u2net_fast/dataloader.py
u2net_fast/model.py
u2net_fast/remover.py
u2net_fast-1.0.0.dist-info/METADATA
u2net_fast-1.0.0.dist-info/WHEEL
u2net_fast-1.0.0.dist-info/licenses/LICENSE
u2net_fast-1.0.0.dist-info/RECORD
