Metadata-Version: 2.1
Name: u2net_fast
Version: 1.0.0
Summary: A re-implementation of U2Net to provide better performance with large images.
Project-URL: Homepage, https://github.com/Steve0320/U2Net-Fast
Project-URL: Issues, https://github.com/Steve0320/U2Net-Fast/issues
Author-email: Steven Bertolucci <srbertol@mtu.edu>
License-File: LICENSE
Classifier: License :: OSI Approved :: MIT License
Classifier: Operating System :: OS Independent
Classifier: Programming Language :: Python :: 3
Requires-Python: >=3.8
Requires-Dist: pillow
Requires-Dist: torch
Requires-Dist: torchvision
Requires-Dist: tqdm
